[
    {
        "type": "message",
        "subtype": "file_share",
        "text": "<@U7RTD502K> uploaded a file: <https:\/\/sysprogroup2.slack.com\/files\/U7RTD502K\/F8AS98FJ7\/_______________12___.png|クラス図第12版.png>",
        "file": {
            "id": "F8AS98FJ7",
            "created": 1512616187,
            "timestamp": 1512616187,
            "name": "クラス図第12版.png",
            "title": "クラス図第12版.png",
            "mimetype": "image\/png",
            "filetype": "png",
            "pretty_type": "PNG",
            "user": "U7RTD502K",
            "editable": false,
            "size": 105234,
            "mode": "hosted",
            "is_external": false,
            "external_type": "",
            "is_public": true,
            "public_url_shared": false,
            "display_as_bot": false,
            "username": "",
            "url_private": "https:\/\/files.slack.com\/files-pri\/T7RMFQPGW-F8AS98FJ7\/_______________12___.png?t=xoxe-263729839574-350180570160-350877415858-3c8147387be955eb724d375ff6fc3014",
            "url_private_download": "https:\/\/files.slack.com\/files-pri\/T7RMFQPGW-F8AS98FJ7\/download\/_______________12___.png?t=xoxe-263729839574-350180570160-350877415858-3c8147387be955eb724d375ff6fc3014",
            "thumb_64": "https:\/\/files.slack.com\/files-tmb\/T7RMFQPGW-F8AS98FJ7-c51a8cc761\/_______________12____64.png?t=xoxe-263729839574-350180570160-350877415858-3c8147387be955eb724d375ff6fc3014",
            "thumb_80": "https:\/\/files.slack.com\/files-tmb\/T7RMFQPGW-F8AS98FJ7-c51a8cc761\/_______________12____80.png?t=xoxe-263729839574-350180570160-350877415858-3c8147387be955eb724d375ff6fc3014",
            "thumb_360": "https:\/\/files.slack.com\/files-tmb\/T7RMFQPGW-F8AS98FJ7-c51a8cc761\/_______________12____360.png?t=xoxe-263729839574-350180570160-350877415858-3c8147387be955eb724d375ff6fc3014",
            "thumb_360_w": 360,
            "thumb_360_h": 265,
            "thumb_480": "https:\/\/files.slack.com\/files-tmb\/T7RMFQPGW-F8AS98FJ7-c51a8cc761\/_______________12____480.png?t=xoxe-263729839574-350180570160-350877415858-3c8147387be955eb724d375ff6fc3014",
            "thumb_480_w": 480,
            "thumb_480_h": 353,
            "thumb_160": "https:\/\/files.slack.com\/files-tmb\/T7RMFQPGW-F8AS98FJ7-c51a8cc761\/_______________12____160.png?t=xoxe-263729839574-350180570160-350877415858-3c8147387be955eb724d375ff6fc3014",
            "thumb_720": "https:\/\/files.slack.com\/files-tmb\/T7RMFQPGW-F8AS98FJ7-c51a8cc761\/_______________12____720.png?t=xoxe-263729839574-350180570160-350877415858-3c8147387be955eb724d375ff6fc3014",
            "thumb_720_w": 720,
            "thumb_720_h": 530,
            "thumb_800": "https:\/\/files.slack.com\/files-tmb\/T7RMFQPGW-F8AS98FJ7-c51a8cc761\/_______________12____800.png?t=xoxe-263729839574-350180570160-350877415858-3c8147387be955eb724d375ff6fc3014",
            "thumb_800_w": 800,
            "thumb_800_h": 589,
            "thumb_960": "https:\/\/files.slack.com\/files-tmb\/T7RMFQPGW-F8AS98FJ7-c51a8cc761\/_______________12____960.png?t=xoxe-263729839574-350180570160-350877415858-3c8147387be955eb724d375ff6fc3014",
            "thumb_960_w": 960,
            "thumb_960_h": 707,
            "thumb_1024": "https:\/\/files.slack.com\/files-tmb\/T7RMFQPGW-F8AS98FJ7-c51a8cc761\/_______________12____1024.png?t=xoxe-263729839574-350180570160-350877415858-3c8147387be955eb724d375ff6fc3014",
            "thumb_1024_w": 1024,
            "thumb_1024_h": 754,
            "image_exif_rotation": 1,
            "original_w": 1337,
            "original_h": 984,
            "permalink": "https:\/\/sysprogroup2.slack.com\/files\/U7RTD502K\/F8AS98FJ7\/_______________12___.png",
            "permalink_public": "https:\/\/slack-files.com\/T7RMFQPGW-F8AS98FJ7-3eeb820969",
            "channels": [],
            "groups": [],
            "ims": [],
            "comments_count": 0
        },
        "user": "U7RTD502K",
        "upload": true,
        "display_as_bot": false,
        "username": "e155407w",
        "bot_id": null,
        "ts": "1512616190.000030"
    }
]