[
    {
        "type": "message",
        "user": "U7RTD502K",
        "text": "<https:\/\/github.com\/HazeyamaLab\/SE17G2>",
        "ts": "1510292151.000163"
    },
    {
        "type": "message",
        "user": "U7QSFDQPN",
        "text": "<https:\/\/gakugei-my.sharepoint.com\/personal\/e155403n_st_u-gakugei_ac_jp\/_layouts\/15\/guestaccess.aspx?guestaccesstoken=kK9B1%2FnQiCyKmn%2Flet6wruLzGVdpY5tFnmLRVdpAlIA%3D&amp;docid=2_1e96563edbd2c45249c997f641c64c6e0&amp;rev=1&amp;e=ab0b7fe33059498a84d2f685980a64d5>",
        "ts": "1510299110.000121"
    }
]